flexibee_export/__init__.py
flexibee_export/xml.py
flexibee_export-0.1.0.dist-info/LICENSE
flexibee_export-0.1.0.dist-info/METADATA
flexibee_export-0.1.0.dist-info/WHEEL
flexibee_export-0.1.0.dist-info/top_level.txt
flexibee_export-0.1.0.dist-info/RECORD
