Metadata-Version: 2.1
Name: flexibee-export
Version: 0.1.0
Summary: FlexiBee xml export package
Home-page: https://github.com/EndevelCZ/flexibee-export.git
Author: Endevel
Author-email: info@endevel.cz
License: UNKNOWN
Platform: UNKNOWN
Classifier: Programming Language :: Python :: 3
Classifier: License :: OSI Approved :: MIT License
Classifier: Operating System :: OS Independent
